signals/__init__.py
signals/_cellmagic.py
signals/_core.py
signals/_version.py
signals-0.1.0.dist-info/METADATA
signals-0.1.0.dist-info/WHEEL
signals-0.1.0.dist-info/RECORD
