Metadata-Version: 2.3
Name: signals
Version: 0.1.0
Summary: A reactive programming library for Python, implementing a signals system similar to @preact/signals
Author-email: Trevor Manz <trevor.j.manz@gmail.com>
Requires-Python: >=3.8
